venv/__init__.py
venv/modal.py
mformodal-1.0.0.dist-info/METADATA
mformodal-1.0.0.dist-info/WHEEL
mformodal-1.0.0.dist-info/top_level.txt
mformodal-1.0.0.dist-info/RECORD
