Metadata-Version: 2.1
Name: mformodal
Version: 1.0.0
Summary: A simple package to create Discord modals
Home-page: https://github.com/sforskeezy/mformodal
Author: sforskeezy | sforskeezy.com
Author-email: sforskeezy@sforskeezy.com
Classifier: Programming Language :: Python :: 3
Classifier: License :: OSI Approved :: MIT License
Classifier: Operating System :: OS Independent
Requires-Python: >=3.6
Requires-Dist: discord.py
